pg_objectserialization.cpython-39-darwin.so
pg_objectserialization-1.0.3.dist-info/METADATA
pg_objectserialization-1.0.3.dist-info/WHEEL
pg_objectserialization-1.0.3.dist-info/top_level.txt
pg_objectserialization-1.0.3.dist-info/RECORD
